{
    "device_type": "Somfy SDN",
    "title": "Somfy curtain motor",
    "group": "curtain",
    "device": {
        "name": "Somfy SDN",
        "id": "somfy",
        "protocol": "somfy",
        "response_timeout_ms": 255,
        "frame_timeout_ms": 10,
        "channels": [
            {
                "name": "Position",
                "reg_type": "position",
                "address": 0,
                "max": 100,
                "type": "range"
            },
            {
                "name": "Status",
                "type": "text",
                "consists_of": [
                    {
                        "reg_type": "param",
                        "address": "0x0E:0:8",
                        "response_header": "0x0F"
                    },
                    {
                        "reg_type": "param",
                        "address": "0x0E:8:8",
                        "response_header": "0x0F"
                    },
                    {
                        "reg_type": "param",
                        "address": "0x0E:16:8",
                        "response_header": "0x0F"
                    },
                    {
                        "reg_type": "param",
                        "address": "0x0E:24:8",
                        "response_header": "0x0F"
                    }
                ]
            },
            {
                "name": "Stop",
                "type": "pushbutton",
                "reg_type": "command",
                "address": "0x02",
                "on_value": "0x0101"
            },
            {
                "name": "Move down",
                "type": "pushbutton",
                "reg_type": "command",
                "address": "0x04",
                "on_value": "0x0A0204"
            },
            {
                "name": "Move up",
                "type": "pushbutton",
                "reg_type": "command",
                "address": "0x04",
                "on_value": "0x0A0304"
            },
            {
                "name": "Delete limits",
                "type": "pushbutton",
                "reg_type": "command",
                "address": "0x11",
                "on_value": "0x04"
            },
            {
                "name": "Set up limit",
                "type": "pushbutton",
                "reg_type": "command",
                "address": "0x11",
                "on_value": "0x010104"
            },
            {
                "name": "Set down limit",
                "type": "pushbutton",
                "reg_type": "command",
                "address": "0x11",
                "on_value": "0x0104"
            },
            {
                "name": "Motor position",
                "type": "text",
                "consists_of": [
                    {
                        "reg_type": "param",
                        "address": "0x0C:0:16",
                        "response_header": "0x0D"
                    },
                    {
                        "reg_type": "param",
                        "address": "0x0C:16:8",
                        "response_header": "0x0D"
                    },
                    {
                        "reg_type": "param",
                        "address": "0x0C:32:8",
                        "response_header": "0x0D"
                    }
                ],
                "enabled": false
            },
            {
                "name": "Limits",
                "type": "text",
                "consists_of": [
                    {
                        "reg_type": "param",
                        "address": "0x21:0:16",
                        "response_header": "0x31"
                    },
                    {
                        "reg_type": "param",
                        "address": "0x21:16:16",
                        "response_header": "0x31"
                    }
                ],
                "enabled": false
            },
            {
                "name": "Direction",
                "reg_type": "param",
                "address": "0x22",
                "response_header": "0x32",
                "enabled": false
            },
            {
                "name": "Rolling speed",
                "type": "text",
                "consists_of": [
                    {
                        "reg_type": "param",
                        "address": "0x23:0:8",
                        "response_header": "0x33"
                    },
                    {
                        "reg_type": "param",
                        "address": "0x23:8:8",
                        "response_header": "0x33"
                    },
                    {
                        "reg_type": "param",
                        "address": "0x23:16:8",
                        "response_header": "0x33"
                    }
                ],
                "enabled": false
            }
        ]
    }
}
